setup.py
babymaker/__init__.py
py_babymaker.egg-info/PKG-INFO
py_babymaker.egg-info/SOURCES.txt
py_babymaker.egg-info/dependency_links.txt
py_babymaker.egg-info/top_level.txt