Metadata-Version: 1.0
Name: py-babymaker
Version: 1.0.1
Summary: py-babymaker
Home-page: https://github.com/SPSCommerce/py-babymaker
Author: pjdecoursey
Author-email: webapps@spscommerce.com
License: MIT
Platform: UNKNOWN
